prefect_soda_core/__init__.py
prefect_soda_core/_version.py
prefect_soda_core/exceptions.py
prefect_soda_core/soda_configuration.py
prefect_soda_core/sodacl_check.py
prefect_soda_core/tasks.py
prefect_soda_core-0.1.8.dist-info/LICENSE
prefect_soda_core-0.1.8.dist-info/METADATA
prefect_soda_core-0.1.8.dist-info/WHEEL
prefect_soda_core-0.1.8.dist-info/top_level.txt
prefect_soda_core-0.1.8.dist-info/RECORD
