Metadata-Version: 2.1
Name: prefect-soda-core
Version: 0.1.8
Summary: Prefect 2.0 collection for Soda Core
Home-page: https://github.com/sodadata/prefect-soda-core
Author: Soda Data NV.
Author-email: vijay@soda.io
License: Apache License 2.0
Keywords: prefect
Classifier: Natural Language :: English
Classifier: Intended Audience :: Developers
Classifier: Intended Audience :: System Administrators
Classifier: License :: OSI Approved :: Apache Software License
Classifier: Programming Language :: Python :: 3 :: Only
Classifier: Programming Language :: Python :: 3.7
Classifier: Programming Language :: Python :: 3.8
Classifier: Programming Language :: Python :: 3.9
Classifier: Programming Language :: Python :: 3.10
Classifier: Topic :: Software Development :: Libraries
Requires-Python: >=3.7
License-File: LICENSE
Requires-Dist: prefect >=2.0.0
Requires-Dist: prefect-shell
Requires-Dist: soda-core
Requires-Dist: pydantic <2
Provides-Extra: athena
Requires-Dist: soda-core-athena ; extra == 'athena'
Provides-Extra: bigquery
Requires-Dist: soda-core-bigquery ; extra == 'bigquery'
Provides-Extra: db2
Requires-Dist: soda-core-db2 ; extra == 'db2'
Provides-Extra: dev
Requires-Dist: pytest ; extra == 'dev'
Requires-Dist: black ; extra == 'dev'
Requires-Dist: flake8 ; extra == 'dev'
Requires-Dist: mypy ; extra == 'dev'
Requires-Dist: mkdocs ; extra == 'dev'
Requires-Dist: mkdocs-material ; extra == 'dev'
Requires-Dist: mkdocstrings[python] ; extra == 'dev'
Requires-Dist: isort ; extra == 'dev'
Requires-Dist: pre-commit ; extra == 'dev'
Requires-Dist: pytest-asyncio ; extra == 'dev'
Requires-Dist: mkdocs-gen-files ; extra == 'dev'
Requires-Dist: interrogate ; extra == 'dev'
Requires-Dist: coverage ; extra == 'dev'
Requires-Dist: pyfakefs ; extra == 'dev'
Requires-Dist: mock ; (python_version < "3.8") and extra == 'dev'
Provides-Extra: mysql
Requires-Dist: soda-core-mysql ; extra == 'mysql'
Provides-Extra: postgres
Requires-Dist: soda-core-postgres ; extra == 'postgres'
Provides-Extra: redshift
Requires-Dist: soda-core-redshift ; extra == 'redshift'
Provides-Extra: snowflake
Requires-Dist: soda-core-snowflake ; extra == 'snowflake'
Provides-Extra: spark-df
Requires-Dist: soda-core-spark-df ; extra == 'spark-df'
Provides-Extra: sqlserver
Requires-Dist: soda-core-sqlserver ; extra == 'sqlserver'
Provides-Extra: trino
Requires-Dist: soda-core-trino ; extra == 'trino'
